<?xml version="1.0" encoding="UTF-8"?>
<results xmlns="http://www.corinet.org/namespaces/CORINETResults">

<execution>

  <network id="N0">
    <values id="N0" type="netInput">
      <cycle config="0" run="0">
        <v i="0">0.1     0       </v>
        <v i="1">0.1     0.75    </v>
      </cycle>
      <cycle config="1" run="0">
        <v i="0">0.2     0       </v>
        <v i="1">0.2     0.75    </v>
      </cycle>
      <cycle config="2" run="0">
        <v i="0">0.4     0       </v>
        <v i="1">0.4     0.75    </v>
      </cycle>
      <cycle config="3" run="0">
        <v i="0">0.8     0       </v>
        <v i="1">0.8     0.75    </v>
      </cycle>
      <cycle config="4" run="0">
        <v i="0">1.6     0       </v>
        <v i="1">1.6     0.75    </v>
      </cycle>
    </values>
    <values id="N0" type="netOutput">
      <cycle config="0" run="0">
        <v i="0" s="0">0       </v>
        <v i="0" s="1">0.0024  </v>
        <v i="0" s="2">0.0004  </v>
        <v i="0" s="3">0.0002  </v>
        <v i="0" s="4">0.0001  </v>
        <v i="0" s="5">0.0001  </v>
        <v i="0" s="6">0.0001  </v>
        <v i="0" s="7">0.0001  </v>
        <v i="0" s="8">0.0001  </v>
        <v i="0" s="9">0.0001  </v>
        <v i="0" s="10">0.0001  </v>
        <v i="0" s="11">0.0001  </v>
        <v i="0" s="12">0.0001  </v>
        <v i="0" s="13">0.0001  </v>
        <v i="0" s="14">0.0001  </v>
        <v i="0" s="15">0.0001  </v>
        <v i="0" s="16">0.0001  </v>
        <v i="0" s="17">0.0001  </v>
        <v i="0" s="18">0.0001  </v>
        <v i="0" s="19">0.0001  </v>
        <v i="0" s="20">0.0001  </v>
        <v i="0" s="21">0.0001  </v>
        <v i="0" s="22">0.0001  </v>
        <v i="0" s="23">0.0001  </v>
        <v i="0" s="24">0.0001  </v>
        <v i="0" s="25">0.0001  </v>
        <v i="1" s="0">0       </v>
        <v i="1" s="1">0.0033  </v>
        <v i="1" s="2">0.0008  </v>
        <v i="1" s="3">0.0004  </v>
        <v i="1" s="4">0.0003  </v>
        <v i="1" s="5">0.0003  </v>
        <v i="1" s="6">0.0003  </v>
        <v i="1" s="7">0.0003  </v>
        <v i="1" s="8">0.0003  </v>
        <v i="1" s="9">0.0003  </v>
        <v i="1" s="10">0.0003  </v>
        <v i="1" s="11">0.0003  </v>
        <v i="1" s="12">0.0003  </v>
        <v i="1" s="13">0.0003  </v>
        <v i="1" s="14">0.0003  </v>
        <v i="1" s="15">0.0003  </v>
        <v i="1" s="16">0.0003  </v>
        <v i="1" s="17">0.0003  </v>
        <v i="1" s="18">0.0003  </v>
        <v i="1" s="19">0.0003  </v>
        <v i="1" s="20">0.0003  </v>
        <v i="1" s="21">0.0003  </v>
        <v i="1" s="22">0.0003  </v>
        <v i="1" s="23">0.0003  </v>
        <v i="1" s="24">0.0003  </v>
        <v i="1" s="25">0.0003  </v>
      </cycle>
      <cycle config="1" run="0">
        <v i="0" s="0">0       </v>
        <v i="0" s="1">0.0048  </v>
        <v i="0" s="2">0.0016  </v>
        <v i="0" s="3">0.001   </v>
        <v i="0" s="4">0.0008  </v>
        <v i="0" s="5">0.0008  </v>
        <v i="0" s="6">0.0007  </v>
        <v i="0" s="7">0.0007  </v>
        <v i="0" s="8">0.0007  </v>
        <v i="0" s="9">0.0007  </v>
        <v i="0" s="10">0.0007  </v>
        <v i="0" s="11">0.0007  </v>
        <v i="0" s="12">0.0007  </v>
        <v i="0" s="13">0.0007  </v>
        <v i="0" s="14">0.0007  </v>
        <v i="0" s="15">0.0007  </v>
        <v i="0" s="16">0.0007  </v>
        <v i="0" s="17">0.0007  </v>
        <v i="0" s="18">0.0007  </v>
        <v i="0" s="19">0.0007  </v>
        <v i="0" s="20">0.0007  </v>
        <v i="0" s="21">0.0007  </v>
        <v i="0" s="22">0.0007  </v>
        <v i="0" s="23">0.0007  </v>
        <v i="0" s="24">0.0007  </v>
        <v i="0" s="25">0.0007  </v>
        <v i="1" s="0">0       </v>
        <v i="1" s="1">0.0066  </v>
        <v i="1" s="2">0.0031  </v>
        <v i="1" s="3">0.0023  </v>
        <v i="1" s="4">0.0021  </v>
        <v i="1" s="5">0.002   </v>
        <v i="1" s="6">0.002   </v>
        <v i="1" s="7">0.0019  </v>
        <v i="1" s="8">0.0019  </v>
        <v i="1" s="9">0.0019  </v>
        <v i="1" s="10">0.0019  </v>
        <v i="1" s="11">0.0018  </v>
        <v i="1" s="12">0.0018  </v>
        <v i="1" s="13">0.0018  </v>
        <v i="1" s="14">0.0018  </v>
        <v i="1" s="15">0.0018  </v>
        <v i="1" s="16">0.0018  </v>
        <v i="1" s="17">0.0018  </v>
        <v i="1" s="18">0.0018  </v>
        <v i="1" s="19">0.0018  </v>
        <v i="1" s="20">0.0018  </v>
        <v i="1" s="21">0.0018  </v>
        <v i="1" s="22">0.0018  </v>
        <v i="1" s="23">0.0018  </v>
        <v i="1" s="24">0.0018  </v>
        <v i="1" s="25">0.0018  </v>
      </cycle>
      <cycle config="2" run="0">
        <v i="0" s="0">0       </v>
        <v i="0" s="1">0.0096  </v>
        <v i="0" s="2">0.0065  </v>
        <v i="0" s="3">0.0063  </v>
        <v i="0" s="4">0.0065  </v>
        <v i="0" s="5">0.0066  </v>
        <v i="0" s="6">0.0066  </v>
        <v i="0" s="7">0.0065  </v>
        <v i="0" s="8">0.0064  </v>
        <v i="0" s="9">0.0063  </v>
        <v i="0" s="10">0.0062  </v>
        <v i="0" s="11">0.0061  </v>
        <v i="0" s="12">0.006   </v>
        <v i="0" s="13">0.006   </v>
        <v i="0" s="14">0.0059  </v>
        <v i="0" s="15">0.0059  </v>
        <v i="0" s="16">0.0059  </v>
        <v i="0" s="17">0.0059  </v>
        <v i="0" s="18">0.0059  </v>
        <v i="0" s="19">0.0059  </v>
        <v i="0" s="20">0.0059  </v>
        <v i="0" s="21">0.0059  </v>
        <v i="0" s="22">0.0059  </v>
        <v i="0" s="23">0.0059  </v>
        <v i="0" s="24">0.0059  </v>
        <v i="0" s="25">0.0059  </v>
        <v i="1" s="0">0       </v>
        <v i="1" s="1">0.0132  </v>
        <v i="1" s="2">0.0122  </v>
        <v i="1" s="3">0.0144  </v>
        <v i="1" s="4">0.0167  </v>
        <v i="1" s="5">0.0181  </v>
        <v i="1" s="6">0.0184  </v>
        <v i="1" s="7">0.0181  </v>
        <v i="1" s="8">0.0175  </v>
        <v i="1" s="9">0.0169  </v>
        <v i="1" s="10">0.0164  </v>
        <v i="1" s="11">0.016   </v>
        <v i="1" s="12">0.0158  </v>
        <v i="1" s="13">0.0156  </v>
        <v i="1" s="14">0.0154  </v>
        <v i="1" s="15">0.0153  </v>
        <v i="1" s="16">0.0153  </v>
        <v i="1" s="17">0.0153  </v>
        <v i="1" s="18">0.0152  </v>
        <v i="1" s="19">0.0152  </v>
        <v i="1" s="20">0.0152  </v>
        <v i="1" s="21">0.0152  </v>
        <v i="1" s="22">0.0152  </v>
        <v i="1" s="23">0.0152  </v>
        <v i="1" s="24">0.0152  </v>
        <v i="1" s="25">0.0152  </v>
      </cycle>
      <cycle config="3" run="0">
        <v i="0" s="0">0       </v>
        <v i="0" s="1">0.0192  </v>
        <v i="0" s="2">0.0255  </v>
        <v i="0" s="3">0.0382  </v>
        <v i="0" s="4">0.0499  </v>
        <v i="0" s="5">0.0558  </v>
        <v i="0" s="6">0.0564  </v>
        <v i="0" s="7">0.0541  </v>
        <v i="0" s="8">0.051   </v>
        <v i="0" s="9">0.0481  </v>
        <v i="0" s="10">0.0459  </v>
        <v i="0" s="11">0.0443  </v>
        <v i="0" s="12">0.0433  </v>
        <v i="0" s="13">0.0426  </v>
        <v i="0" s="14">0.0422  </v>
        <v i="0" s="15">0.042   </v>
        <v i="0" s="16">0.0419  </v>
        <v i="0" s="17">0.0418  </v>
        <v i="0" s="18">0.0418  </v>
        <v i="0" s="19">0.0419  </v>
        <v i="0" s="20">0.0419  </v>
        <v i="0" s="21">0.0419  </v>
        <v i="0" s="22">0.0419  </v>
        <v i="0" s="23">0.0419  </v>
        <v i="0" s="24">0.042   </v>
        <v i="0" s="25">0.042   </v>
        <v i="1" s="0">0       </v>
        <v i="1" s="1">0.0264  </v>
        <v i="1" s="2">0.0473  </v>
        <v i="1" s="3">0.0852  </v>
        <v i="1" s="4">0.1188  </v>
        <v i="1" s="5">0.1319  </v>
        <v i="1" s="6">0.1282  </v>
        <v i="1" s="7">0.1178  </v>
        <v i="1" s="8">0.1073  </v>
        <v i="1" s="9">0.0989  </v>
        <v i="1" s="10">0.0931  </v>
        <v i="1" s="11">0.0893  </v>
        <v i="1" s="12">0.0871  </v>
        <v i="1" s="13">0.0859  </v>
        <v i="1" s="14">0.0855  </v>
        <v i="1" s="15">0.0854  </v>
        <v i="1" s="16">0.0855  </v>
        <v i="1" s="17">0.0857  </v>
        <v i="1" s="18">0.0859  </v>
        <v i="1" s="19">0.0861  </v>
        <v i="1" s="20">0.0862  </v>
        <v i="1" s="21">0.0863  </v>
        <v i="1" s="22">0.0864  </v>
        <v i="1" s="23">0.0864  </v>
        <v i="1" s="24">0.0865  </v>
        <v i="1" s="25">0.0865  </v>
      </cycle>
      <cycle config="4" run="0">
        <v i="0" s="0">0       </v>
        <v i="0" s="1">0.0384  </v>
        <v i="0" s="2">0.0974  </v>
        <v i="0" s="3">0.1814  </v>
        <v i="0" s="4">0.2387  </v>
        <v i="0" s="5">0.2634  </v>
        <v i="0" s="6">0.2676  </v>
        <v i="0" s="7">0.2564  </v>
        <v i="0" s="8">0.2372  </v>
        <v i="0" s="9">0.2177  </v>
        <v i="0" s="10">0.2016  </v>
        <v i="0" s="11">0.1899  </v>
        <v i="0" s="12">0.1824  </v>
        <v i="0" s="13">0.1782  </v>
        <v i="0" s="14">0.1764  </v>
        <v i="0" s="15">0.1761  </v>
        <v i="0" s="16">0.1766  </v>
        <v i="0" s="17">0.1776  </v>
        <v i="0" s="18">0.1786  </v>
        <v i="0" s="19">0.1796  </v>
        <v i="0" s="20">0.1803  </v>
        <v i="0" s="21">0.1809  </v>
        <v i="0" s="22">0.1812  </v>
        <v i="0" s="23">0.1814  </v>
        <v i="0" s="24">0.1815  </v>
        <v i="0" s="25">0.1815  </v>
        <v i="1" s="0">0       </v>
        <v i="1" s="1">0.0528  </v>
        <v i="1" s="2">0.1359  </v>
        <v i="1" s="3">0.2116  </v>
        <v i="1" s="4">0.2539  </v>
        <v i="1" s="5">0.2677  </v>
        <v i="1" s="6">0.2666  </v>
        <v i="1" s="7">0.2603  </v>
        <v i="1" s="8">0.2533  </v>
        <v i="1" s="9">0.2476  </v>
        <v i="1" s="10">0.2432  </v>
        <v i="1" s="11">0.2403  </v>
        <v i="1" s="12">0.2383  </v>
        <v i="1" s="13">0.237   </v>
        <v i="1" s="14">0.2363  </v>
        <v i="1" s="15">0.2358  </v>
        <v i="1" s="16">0.2355  </v>
        <v i="1" s="17">0.2354  </v>
        <v i="1" s="18">0.2353  </v>
        <v i="1" s="19">0.2353  </v>
        <v i="1" s="20">0.2353  </v>
        <v i="1" s="21">0.2353  </v>
        <v i="1" s="22">0.2353  </v>
        <v i="1" s="23">0.2353  </v>
        <v i="1" s="24">0.2353  </v>
        <v i="1" s="25">0.2353  </v>
      </cycle>
    </values>
  </network>

  <task id="STIMULUS"/>

  <task id="BIAS"/>

</execution>

</results>

